setup.py
pyimage/__init__.py
pyimage/pipeline.py
pyimage.egg-info/PKG-INFO
pyimage.egg-info/SOURCES.txt
pyimage.egg-info/dependency_links.txt
pyimage.egg-info/requires.txt
pyimage.egg-info/top_level.txt