Metadata-Version: 1.0
Name: pyimage
Version: 0.1.1
Summary: A Python library for image processing
Home-page: https://github.com/jyt109/pyimage
Author: Jeffrey Tang
Author-email: jeffrey.tang09@gmail.com
License: MIT
Keywords: image processing pipeline
Platform: UNKNOWN
